brunospackage/__init__.py
brunospackage/functions.py
brunospackage-0.0.9.dist-info/METADATA
brunospackage-0.0.9.dist-info/WHEEL
brunospackage-0.0.9.dist-info/top_level.txt
brunospackage-0.0.9.dist-info/RECORD
