Metadata-Version: 2.1
Name: brunospackage
Version: 0.0.9
Summary: Helper functions that I use often
Author: Bruno Tacchi
Author-email: bruno_tacchi@hotmail.com
Keywords: python,first package
Classifier: Development Status :: 3 - Alpha
Classifier: Intended Audience :: Education
Classifier: Programming Language :: Python :: 2
Classifier: Programming Language :: Python :: 3
Classifier: Operating System :: MacOS :: MacOS X
Classifier: Operating System :: Microsoft :: Windows
Requires-Dist: matplotlib
Requires-Dist: pandas
